{"meta": {"init": "random", "task_type": "hard", "portion": 10.0, "seed": 38, "lr": 7e-06, "epoch": 20, "aug_key": "aug4"}, "train_steps": [{"step": 0, "epoch": 0, "train_loss": 1.954948770588842}, {"step": 1, "epoch": 1, "train_loss": 1.8855060338974}, {"step": 2, "epoch": 1, "train_loss": 1.924773931503296}, {"step": 3, "epoch": 1, "train_loss": 1.768387794494629}, {"step": 4, "epoch": 1, "train_loss": 1.8433188199996948}, {"step": 5, "epoch": 1, "train_loss": 1.8234529495239258}, {"step": 6, "epoch": 1, "train_loss": 1.7688612937927246}, {"step": 7, "epoch": 1, "train_loss": 1.7922378778457642}, {"step": 8, "epoch": 1, "train_loss": 1.8167253732681274}, {"step": 9, "epoch": 1, "train_loss": 1.8601665496826172}, {"step": 10, "epoch": 1, "train_loss": 1.7377002239227295}, {"step": 11, "epoch": 1, "train_loss": 1.7685365676879883}, {"step": 12, "epoch": 1, "train_loss": 1.7457528114318848}, {"step": 13, "epoch": 1, "train_loss": 1.769117832183838}, {"step": 14, "epoch": 1, "train_loss": 1.7610408067703247}, {"step": 15, "epoch": 1, "train_loss": 1.8192253112792969}, {"step": 16, "epoch": 1, "train_loss": 1.7143973112106323}, {"step": 17, "epoch": 1, "train_loss": 1.769761085510254}, {"step": 18, "epoch": 1, "train_loss": 1.9470727443695068}, {"step": 19, "epoch": 1, "train_loss": 1.7427116632461548}, {"step": 20, "epoch": 1, "train_loss": 1.6860121488571167}, {"step": 21, "epoch": 1, "train_loss": 1.7459852695465088}, {"step": 22, "epoch": 1, "train_loss": 1.7863644361495972}, {"step": 23, "epoch": 1, "train_loss": 1.7274219989776611}, {"step": 24, "epoch": 1, "train_loss": 1.7666863203048706}, {"step": 25, "epoch": 1, "train_loss": 1.717705249786377}, {"step": 26, "epoch": 1, "train_loss": 1.6008446216583252}, {"step": 27, "epoch": 1, "train_loss": 1.8100156784057617}, {"step": 28, "epoch": 1, "train_loss": 1.5203027725219727}, {"step": 29, "epoch": 1, "train_loss": 1.7872422933578491}, {"step": 30, "epoch": 1, "train_loss": 1.660701036453247}, {"step": 31, "epoch": 1, "train_loss": 1.7445191144943237}, {"step": 32, "epoch": 1, "train_loss": 1.7569912672042847}, {"step": 33, "epoch": 1, "train_loss": 1.7723028659820557}, {"step": 34, "epoch": 1, "train_loss": 1.8091726303100586}, {"step": 35, "epoch": 1, "train_loss": 1.7509567737579346}, {"step": 36, "epoch": 1, "train_loss": 1.6833609342575073}, {"step": 37, "epoch": 1, "train_loss": 1.6057618856430054}, {"step": 38, "epoch": 1, "train_loss": 1.5376505851745605}, {"step": 39, "epoch": 1, "train_loss": 1.69999361038208}, {"step": 40, "epoch": 1, "train_loss": 1.550170660018921}, {"step": 41, "epoch": 1, "train_loss": 1.5243958234786987}, {"step": 42, "epoch": 1, "train_loss": 1.8441165685653687}, {"step": 43, "epoch": 1, "train_loss": 1.5419880151748657}, {"step": 44, "epoch": 1, "train_loss": 1.8351013660430908}, {"step": 45, "epoch": 1, "train_loss": 1.798065185546875}, {"step": 46, "epoch": 1, "train_loss": 1.496619701385498}, {"step": 47, "epoch": 1, "train_loss": 1.7402048110961914}, {"step": 48, "epoch": 1, "train_loss": 1.6874253749847412}, {"step": 49, "epoch": 1, "train_loss": 1.7433806657791138}, {"step": 50, "epoch": 1, "train_loss": 1.6447291374206543}, {"step": 51, "epoch": 1, "train_loss": 1.610838532447815}, {"step": 52, "epoch": 2, "train_loss": 1.7500078678131104}, {"step": 53, "epoch": 2, "train_loss": 1.600819706916809}, {"step": 54, "epoch": 2, "train_loss": 1.7167267799377441}, {"step": 55, "epoch": 2, "train_loss": 1.5539120435714722}, {"step": 56, "epoch": 2, "train_loss": 1.6464482545852661}, {"step": 57, "epoch": 2, "train_loss": 1.6097419261932373}, {"step": 58, "epoch": 2, "train_loss": 1.4754934310913086}, {"step": 59, "epoch": 2, "train_loss": 1.4300085306167603}, {"step": 60, "epoch": 2, "train_loss": 1.5749903917312622}, {"step": 61, "epoch": 2, "train_loss": 1.653340220451355}, {"step": 62, "epoch": 2, "train_loss": 1.504482626914978}, {"step": 63, "epoch": 2, "train_loss": 1.5053350925445557}, {"step": 64, "epoch": 2, "train_loss": 1.4837566614151}, {"step": 65, "epoch": 2, "train_loss": 1.4177439212799072}, {"step": 66, "epoch": 2, "train_loss": 1.4230844974517822}, {"step": 67, "epoch": 2, "train_loss": 1.8001781702041626}, {"step": 68, "epoch": 2, "train_loss": 1.8992421627044678}, {"step": 69, "epoch": 2, "train_loss": 1.4484771490097046}, {"step": 70, "epoch": 2, "train_loss": 1.4748364686965942}, {"step": 71, "epoch": 2, "train_loss": 1.413853406906128}, {"step": 72, "epoch": 2, "train_loss": 1.488592505455017}, {"step": 73, "epoch": 2, "train_loss": 1.7798594236373901}, {"step": 74, "epoch": 2, "train_loss": 1.621986985206604}, {"step": 75, "epoch": 2, "train_loss": 1.9670015573501587}, {"step": 76, "epoch": 2, "train_loss": 1.5488245487213135}, {"step": 77, "epoch": 2, "train_loss": 1.6922361850738525}, {"step": 78, "epoch": 2, "train_loss": 1.5271037817001343}, {"step": 79, "epoch": 2, "train_loss": 1.6117585897445679}, {"step": 80, "epoch": 2, "train_loss": 1.714735746383667}, {"step": 81, "epoch": 2, "train_loss": 1.8127821683883667}, {"step": 82, "epoch": 2, "train_loss": 1.5617128610610962}, {"step": 83, "epoch": 2, "train_loss": 1.6081326007843018}, {"step": 84, "epoch": 2, "train_loss": 1.4667097330093384}, {"step": 85, "epoch": 2, "train_loss": 1.4170066118240356}, {"step": 86, "epoch": 2, "train_loss": 1.485137939453125}, {"step": 87, "epoch": 2, "train_loss": 1.7160896062850952}, {"step": 88, "epoch": 2, "train_loss": 1.4018222093582153}, {"step": 89, "epoch": 2, "train_loss": 1.598706603050232}, {"step": 90, "epoch": 2, "train_loss": 1.611440896987915}, {"step": 91, "epoch": 2, "train_loss": 1.4483710527420044}, {"step": 92, "epoch": 2, "train_loss": 1.561697244644165}, {"step": 93, "epoch": 2, "train_loss": 1.5174851417541504}, {"step": 94, "epoch": 2, "train_loss": 1.6054840087890625}, {"step": 95, "epoch": 2, "train_loss": 1.5175788402557373}, {"step": 96, "epoch": 2, "train_loss": 1.668951392173767}, {"step": 97, "epoch": 2, "train_loss": 1.630483627319336}, {"step": 98, "epoch": 2, "train_loss": 1.7163424491882324}, {"step": 99, "epoch": 2, "train_loss": 1.2719719409942627}, {"step": 100, "epoch": 2, "train_loss": 1.6011124849319458}, {"step": 101, "epoch": 2, "train_loss": 1.595970869064331}, {"step": 102, "epoch": 2, "train_loss": 1.4467018842697144}, {"step": 103, "epoch": 3, "train_loss": 1.301357626914978}, {"step": 104, "epoch": 3, "train_loss": 1.5143369436264038}, {"step": 105, "epoch": 3, "train_loss": 1.632994532585144}, {"step": 106, "epoch": 3, "train_loss": 1.6976759433746338}, {"step": 107, "epoch": 3, "train_loss": 1.4869663715362549}, {"step": 108, "epoch": 3, "train_loss": 1.5603382587432861}, {"step": 109, "epoch": 3, "train_loss": 1.3755621910095215}, {"step": 110, "epoch": 3, "train_loss": 1.3295269012451172}, {"step": 111, "epoch": 3, "train_loss": 1.6600213050842285}, {"step": 112, "epoch": 3, "train_loss": 1.5017757415771484}, {"step": 113, "epoch": 3, "train_loss": 1.4038848876953125}, {"step": 114, "epoch": 3, "train_loss": 1.313584566116333}, {"step": 115, "epoch": 3, "train_loss": 1.3911125659942627}, {"step": 116, "epoch": 3, "train_loss": 1.5437366962432861}, {"step": 117, "epoch": 3, "train_loss": 1.442996621131897}, {"step": 118, "epoch": 3, "train_loss": 1.6002379655838013}, {"step": 119, "epoch": 3, "train_loss": 1.6163455247879028}, {"step": 120, "epoch": 3, "train_loss": 1.426284909248352}, {"step": 121, "epoch": 3, "train_loss": 1.8192254304885864}, {"step": 122, "epoch": 3, "train_loss": 1.6063657999038696}, {"step": 123, "epoch": 3, "train_loss": 1.5443052053451538}, {"step": 124, "epoch": 3, "train_loss": 1.5287688970565796}, {"step": 125, "epoch": 3, "train_loss": 1.55898118019104}, {"step": 126, "epoch": 3, "train_loss": 1.6837769746780396}, {"step": 127, "epoch": 3, "train_loss": 1.754220724105835}, {"step": 128, "epoch": 3, "train_loss": 1.6659371852874756}, {"step": 129, "epoch": 3, "train_loss": 1.4018594026565552}, {"step": 130, "epoch": 3, "train_loss": 1.4912083148956299}, {"step": 131, "epoch": 3, "train_loss": 1.5140050649642944}, {"step": 132, "epoch": 3, "train_loss": 1.6197869777679443}, {"step": 133, "epoch": 3, "train_loss": 1.5688941478729248}, {"step": 134, "epoch": 3, "train_loss": 1.6520824432373047}, {"step": 135, "epoch": 3, "train_loss": 1.1808171272277832}, {"step": 136, "epoch": 3, "train_loss": 1.6660914421081543}, {"step": 137, "epoch": 3, "train_loss": 1.5315372943878174}, {"step": 138, "epoch": 3, "train_loss": 1.5356403589248657}, {"step": 139, "epoch": 3, "train_loss": 1.4695940017700195}, {"step": 140, "epoch": 3, "train_loss": 1.4231611490249634}, {"step": 141, "epoch": 3, "train_loss": 1.4550672769546509}, {"step": 142, "epoch": 3, "train_loss": 1.6131141185760498}, {"step": 143, "epoch": 3, "train_loss": 1.3895554542541504}, {"step": 144, "epoch": 3, "train_loss": 1.5592890977859497}, {"step": 145, "epoch": 3, "train_loss": 1.3962342739105225}, {"step": 146, "epoch": 3, "train_loss": 1.6252094507217407}, {"step": 147, "epoch": 3, "train_loss": 1.469477653503418}, {"step": 148, "epoch": 3, "train_loss": 1.494271159172058}, {"step": 149, "epoch": 3, "train_loss": 1.4238957166671753}, {"step": 150, "epoch": 3, "train_loss": 1.4360071420669556}, {"step": 151, "epoch": 3, "train_loss": 1.5816233158111572}, {"step": 152, "epoch": 3, "train_loss": 1.5316969156265259}, {"step": 153, "epoch": 3, "train_loss": 1.3081709146499634}, {"step": 154, "epoch": 4, "train_loss": 1.332973837852478}, {"step": 155, "epoch": 4, "train_loss": 1.5611333847045898}, {"step": 156, "epoch": 4, "train_loss": 1.3141932487487793}, {"step": 157, "epoch": 4, "train_loss": 1.556185245513916}, {"step": 158, "epoch": 4, "train_loss": 1.760322093963623}, {"step": 159, "epoch": 4, "train_loss": 1.4576258659362793}, {"step": 160, "epoch": 4, "train_loss": 1.6017868518829346}, {"step": 161, "epoch": 4, "train_loss": 1.2862128019332886}, {"step": 162, "epoch": 4, "train_loss": 1.395190715789795}, {"step": 163, "epoch": 4, "train_loss": 1.2943246364593506}, {"step": 164, "epoch": 4, "train_loss": 1.4625164270401}, {"step": 165, "epoch": 4, "train_loss": 1.6135313510894775}, {"step": 166, "epoch": 4, "train_loss": 1.3616081476211548}, {"step": 167, "epoch": 4, "train_loss": 1.4419276714324951}, {"step": 168, "epoch": 4, "train_loss": 1.4849308729171753}, {"step": 169, "epoch": 4, "train_loss": 1.3812488317489624}, {"step": 170, "epoch": 4, "train_loss": 1.5279643535614014}, {"step": 171, "epoch": 4, "train_loss": 1.3853555917739868}, {"step": 172, "epoch": 4, "train_loss": 1.4109293222427368}, {"step": 173, "epoch": 4, "train_loss": 1.3702222108840942}, {"step": 174, "epoch": 4, "train_loss": 1.311432123184204}, {"step": 175, "epoch": 4, "train_loss": 1.3930755853652954}, {"step": 176, "epoch": 4, "train_loss": 1.4525777101516724}, {"step": 177, "epoch": 4, "train_loss": 1.481024980545044}, {"step": 178, "epoch": 4, "train_loss": 1.4541624784469604}, {"step": 179, "epoch": 4, "train_loss": 1.512010097503662}, {"step": 180, "epoch": 4, "train_loss": 1.4853869676589966}, {"step": 181, "epoch": 4, "train_loss": 1.4152491092681885}, {"step": 182, "epoch": 4, "train_loss": 1.4047483205795288}, {"step": 183, "epoch": 4, "train_loss": 1.3352587223052979}, {"step": 184, "epoch": 4, "train_loss": 1.5436969995498657}, {"step": 185, "epoch": 4, "train_loss": 1.5227011442184448}, {"step": 186, "epoch": 4, "train_loss": 1.522392988204956}, {"step": 187, "epoch": 4, "train_loss": 1.7153666019439697}, {"step": 188, "epoch": 4, "train_loss": 1.6170923709869385}, {"step": 189, "epoch": 4, "train_loss": 1.3802366256713867}, {"step": 190, "epoch": 4, "train_loss": 1.305424451828003}, {"step": 191, "epoch": 4, "train_loss": 1.4835697412490845}, {"step": 192, "epoch": 4, "train_loss": 1.2819331884384155}, {"step": 193, "epoch": 4, "train_loss": 1.6920440196990967}, {"step": 194, "epoch": 4, "train_loss": 1.3537436723709106}, {"step": 195, "epoch": 4, "train_loss": 1.3269788026809692}, {"step": 196, "epoch": 4, "train_loss": 1.6462140083312988}, {"step": 197, "epoch": 4, "train_loss": 1.4757848978042603}, {"step": 198, "epoch": 4, "train_loss": 1.2052361965179443}, {"step": 199, "epoch": 4, "train_loss": 1.4311398267745972}, {"step": 200, "epoch": 4, "train_loss": 1.8218047618865967}, {"step": 201, "epoch": 4, "train_loss": 1.2555818557739258}, {"step": 202, "epoch": 4, "train_loss": 1.5615565776824951}, {"step": 203, "epoch": 4, "train_loss": 1.4200180768966675}, {"step": 204, "epoch": 4, "train_loss": 1.7471376657485962}, {"step": 205, "epoch": 5, "train_loss": 1.4946131706237793}, {"step": 206, "epoch": 5, "train_loss": 1.3258612155914307}, {"step": 207, "epoch": 5, "train_loss": 1.4354617595672607}, {"step": 208, "epoch": 5, "train_loss": 1.1795804500579834}, {"step": 209, "epoch": 5, "train_loss": 1.2773810625076294}, {"step": 210, "epoch": 5, "train_loss": 1.633628249168396}, {"step": 211, "epoch": 5, "train_loss": 1.546334147453308}, {"step": 212, "epoch": 5, "train_loss": 1.5518957376480103}, {"step": 213, "epoch": 5, "train_loss": 1.4795128107070923}, {"step": 214, "epoch": 5, "train_loss": 1.2878191471099854}, {"step": 215, "epoch": 5, "train_loss": 1.5149800777435303}, {"step": 216, "epoch": 5, "train_loss": 1.0759782791137695}, {"step": 217, "epoch": 5, "train_loss": 1.240749478340149}, {"step": 218, "epoch": 5, "train_loss": 1.2003017663955688}, {"step": 219, "epoch": 5, "train_loss": 1.383466124534607}, {"step": 220, "epoch": 5, "train_loss": 1.4193274974822998}, {"step": 221, "epoch": 5, "train_loss": 1.484062671661377}, {"step": 222, "epoch": 5, "train_loss": 1.2893556356430054}, {"step": 223, "epoch": 5, "train_loss": 1.5306380987167358}, {"step": 224, "epoch": 5, "train_loss": 1.2559465169906616}, {"step": 225, "epoch": 5, "train_loss": 1.642657995223999}, {"step": 226, "epoch": 5, "train_loss": 1.6422632932662964}, {"step": 227, "epoch": 5, "train_loss": 1.4693455696105957}, {"step": 228, "epoch": 5, "train_loss": 1.5351134538650513}, {"step": 229, "epoch": 5, "train_loss": 1.4747065305709839}, {"step": 230, "epoch": 5, "train_loss": 1.530041217803955}, {"step": 231, "epoch": 5, "train_loss": 1.6445494890213013}, {"step": 232, "epoch": 5, "train_loss": 1.6028531789779663}, {"step": 233, "epoch": 5, "train_loss": 1.477942705154419}, {"step": 234, "epoch": 5, "train_loss": 1.516086220741272}, {"step": 235, "epoch": 5, "train_loss": 1.2255971431732178}, {"step": 236, "epoch": 5, "train_loss": 1.5710430145263672}, {"step": 237, "epoch": 5, "train_loss": 1.3526434898376465}, {"step": 238, "epoch": 5, "train_loss": 1.4534146785736084}, {"step": 239, "epoch": 5, "train_loss": 1.5692989826202393}, {"step": 240, "epoch": 5, "train_loss": 1.4493085145950317}, {"step": 241, "epoch": 5, "train_loss": 1.3473843336105347}, {"step": 242, "epoch": 5, "train_loss": 1.2336938381195068}, {"step": 243, "epoch": 5, "train_loss": 1.5347474813461304}, {"step": 244, "epoch": 5, "train_loss": 1.339388370513916}, {"step": 245, "epoch": 5, "train_loss": 1.1116615533828735}, {"step": 246, "epoch": 5, "train_loss": 1.4827558994293213}, {"step": 247, "epoch": 5, "train_loss": 1.5185816287994385}, {"step": 248, "epoch": 5, "train_loss": 1.3565118312835693}, {"step": 249, "epoch": 5, "train_loss": 1.1915709972381592}, {"step": 250, "epoch": 5, "train_loss": 1.4655935764312744}, {"step": 251, "epoch": 5, "train_loss": 1.3128021955490112}, {"step": 252, "epoch": 5, "train_loss": 1.3716118335723877}, {"step": 253, "epoch": 5, "train_loss": 1.4602553844451904}, {"step": 254, "epoch": 5, "train_loss": 1.2185513973236084}, {"step": 255, "epoch": 5, "train_loss": 1.3760768175125122}, {"step": 256, "epoch": 6, "train_loss": 1.2538704872131348}, {"step": 257, "epoch": 6, "train_loss": 1.2889260053634644}, {"step": 258, "epoch": 6, "train_loss": 1.283694863319397}, {"step": 259, "epoch": 6, "train_loss": 1.3747575283050537}, {"step": 260, "epoch": 6, "train_loss": 1.3105533123016357}, {"step": 261, "epoch": 6, "train_loss": 1.365665316581726}, {"step": 262, "epoch": 6, "train_loss": 1.352866530418396}, {"step": 263, "epoch": 6, "train_loss": 1.2394787073135376}, {"step": 264, "epoch": 6, "train_loss": 1.1742693185806274}, {"step": 265, "epoch": 6, "train_loss": 1.4024593830108643}, {"step": 266, "epoch": 6, "train_loss": 1.3179198503494263}, {"step": 267, "epoch": 6, "train_loss": 1.246078610420227}, {"step": 268, "epoch": 6, "train_loss": 1.4008386135101318}, {"step": 269, "epoch": 6, "train_loss": 1.275858998298645}, {"step": 270, "epoch": 6, "train_loss": 1.4019516706466675}, {"step": 271, "epoch": 6, "train_loss": 1.4359183311462402}, {"step": 272, "epoch": 6, "train_loss": 1.470815658569336}, {"step": 273, "epoch": 6, "train_loss": 1.4313114881515503}, {"step": 274, "epoch": 6, "train_loss": 1.263148546218872}, {"step": 275, "epoch": 6, "train_loss": 1.3471379280090332}, {"step": 276, "epoch": 6, "train_loss": 1.4033457040786743}, {"step": 277, "epoch": 6, "train_loss": 1.4521489143371582}, {"step": 278, "epoch": 6, "train_loss": 1.5978009700775146}, {"step": 279, "epoch": 6, "train_loss": 1.2857401371002197}, {"step": 280, "epoch": 6, "train_loss": 1.1114237308502197}, {"step": 281, "epoch": 6, "train_loss": 1.4514570236206055}, {"step": 282, "epoch": 6, "train_loss": 1.5571388006210327}, {"step": 283, "epoch": 6, "train_loss": 1.1413195133209229}, {"step": 284, "epoch": 6, "train_loss": 1.3783605098724365}, {"step": 285, "epoch": 6, "train_loss": 1.1132792234420776}, {"step": 286, "epoch": 6, "train_loss": 1.4845551252365112}, {"step": 287, "epoch": 6, "train_loss": 1.6879905462265015}, {"step": 288, "epoch": 6, "train_loss": 1.6150670051574707}, {"step": 289, "epoch": 6, "train_loss": 1.1741224527359009}, {"step": 290, "epoch": 6, "train_loss": 1.190629005432129}, {"step": 291, "epoch": 6, "train_loss": 1.2312780618667603}, {"step": 292, "epoch": 6, "train_loss": 1.5024598836898804}, {"step": 293, "epoch": 6, "train_loss": 1.5144681930541992}, {"step": 294, "epoch": 6, "train_loss": 1.4089961051940918}, {"step": 295, "epoch": 6, "train_loss": 1.5571521520614624}, {"step": 296, "epoch": 6, "train_loss": 1.5552794933319092}, {"step": 297, "epoch": 6, "train_loss": 1.3599903583526611}, {"step": 298, "epoch": 6, "train_loss": 1.345082402229309}, {"step": 299, "epoch": 6, "train_loss": 1.7969698905944824}, {"step": 300, "epoch": 6, "train_loss": 0.9993575215339661}, {"step": 301, "epoch": 6, "train_loss": 1.4070063829421997}, {"step": 302, "epoch": 6, "train_loss": 1.4195307493209839}, {"step": 303, "epoch": 6, "train_loss": 1.7433292865753174}, {"step": 304, "epoch": 6, "train_loss": 1.1724121570587158}, {"step": 305, "epoch": 6, "train_loss": 1.4186725616455078}, {"step": 306, "epoch": 6, "train_loss": 1.3871936798095703}, {"step": 307, "epoch": 7, "train_loss": 1.4852536916732788}, {"step": 308, "epoch": 7, "train_loss": 1.2170884609222412}, {"step": 309, "epoch": 7, "train_loss": 1.6286077499389648}, {"step": 310, "epoch": 7, "train_loss": 1.2661136388778687}, {"step": 311, "epoch": 7, "train_loss": 1.4636119604110718}, {"step": 312, "epoch": 7, "train_loss": 1.447343111038208}, {"step": 313, "epoch": 7, "train_loss": 1.347184658050537}, {"step": 314, "epoch": 7, "train_loss": 1.3650248050689697}, {"step": 315, "epoch": 7, "train_loss": 1.3063949346542358}, {"step": 316, "epoch": 7, "train_loss": 1.338955044746399}, {"step": 317, "epoch": 7, "train_loss": 1.0211584568023682}, {"step": 318, "epoch": 7, "train_loss": 1.22316575050354}, {"step": 319, "epoch": 7, "train_loss": 1.5934244394302368}, {"step": 320, "epoch": 7, "train_loss": 1.4231624603271484}, {"step": 321, "epoch": 7, "train_loss": 1.2277759313583374}, {"step": 322, "epoch": 7, "train_loss": 1.2631516456604004}, {"step": 323, "epoch": 7, "train_loss": 1.3383586406707764}, {"step": 324, "epoch": 7, "train_loss": 1.3855350017547607}, {"step": 325, "epoch": 7, "train_loss": 1.3174049854278564}, {"step": 326, "epoch": 7, "train_loss": 1.5330733060836792}, {"step": 327, "epoch": 7, "train_loss": 1.3968464136123657}, {"step": 328, "epoch": 7, "train_loss": 1.375308632850647}, {"step": 329, "epoch": 7, "train_loss": 1.4355884790420532}, {"step": 330, "epoch": 7, "train_loss": 1.233263611793518}, {"step": 331, "epoch": 7, "train_loss": 1.4821285009384155}, {"step": 332, "epoch": 7, "train_loss": 1.509765386581421}, {"step": 333, "epoch": 7, "train_loss": 1.3765697479248047}, {"step": 334, "epoch": 7, "train_loss": 1.513038992881775}, {"step": 335, "epoch": 7, "train_loss": 1.4305129051208496}, {"step": 336, "epoch": 7, "train_loss": 1.3316988945007324}, {"step": 337, "epoch": 7, "train_loss": 1.5393781661987305}, {"step": 338, "epoch": 7, "train_loss": 1.220939040184021}, {"step": 339, "epoch": 7, "train_loss": 1.4402623176574707}, {"step": 340, "epoch": 7, "train_loss": 1.1347143650054932}, {"step": 341, "epoch": 7, "train_loss": 1.1658620834350586}, {"step": 342, "epoch": 7, "train_loss": 1.183631181716919}, {"step": 343, "epoch": 7, "train_loss": 1.651564121246338}, {"step": 344, "epoch": 7, "train_loss": 1.2072560787200928}, {"step": 345, "epoch": 7, "train_loss": 1.092837929725647}, {"step": 346, "epoch": 7, "train_loss": 1.3301550149917603}, {"step": 347, "epoch": 7, "train_loss": 1.5633238554000854}, {"step": 348, "epoch": 7, "train_loss": 1.2559962272644043}, {"step": 349, "epoch": 7, "train_loss": 1.2657297849655151}, {"step": 350, "epoch": 7, "train_loss": 1.2088743448257446}, {"step": 351, "epoch": 7, "train_loss": 1.5017447471618652}, {"step": 352, "epoch": 7, "train_loss": 1.401985764503479}, {"step": 353, "epoch": 7, "train_loss": 1.039448618888855}, {"step": 354, "epoch": 7, "train_loss": 1.3988127708435059}, {"step": 355, "epoch": 7, "train_loss": 1.5338811874389648}, {"step": 356, "epoch": 7, "train_loss": 1.2831058502197266}, {"step": 357, "epoch": 7, "train_loss": 1.1510528326034546}, {"step": 358, "epoch": 8, "train_loss": 1.0374367237091064}, {"step": 359, "epoch": 8, "train_loss": 1.4612637758255005}, {"step": 360, "epoch": 8, "train_loss": 1.2723445892333984}, {"step": 361, "epoch": 8, "train_loss": 1.2906099557876587}, {"step": 362, "epoch": 8, "train_loss": 1.4123570919036865}, {"step": 363, "epoch": 8, "train_loss": 1.4850274324417114}, {"step": 364, "epoch": 8, "train_loss": 1.0678133964538574}, {"step": 365, "epoch": 8, "train_loss": 1.4180786609649658}, {"step": 366, "epoch": 8, "train_loss": 1.4362648725509644}, {"step": 367, "epoch": 8, "train_loss": 1.1049871444702148}, {"step": 368, "epoch": 8, "train_loss": 1.1582767963409424}, {"step": 369, "epoch": 8, "train_loss": 1.3208011388778687}, {"step": 370, "epoch": 8, "train_loss": 1.6148415803909302}, {"step": 371, "epoch": 8, "train_loss": 1.2789920568466187}, {"step": 372, "epoch": 8, "train_loss": 1.1699424982070923}, {"step": 373, "epoch": 8, "train_loss": 1.3222384452819824}, {"step": 374, "epoch": 8, "train_loss": 1.1466912031173706}, {"step": 375, "epoch": 8, "train_loss": 1.3030871152877808}, {"step": 376, "epoch": 8, "train_loss": 1.2784268856048584}, {"step": 377, "epoch": 8, "train_loss": 1.0288480520248413}, {"step": 378, "epoch": 8, "train_loss": 1.0894900560379028}, {"step": 379, "epoch": 8, "train_loss": 1.3971878290176392}, {"step": 380, "epoch": 8, "train_loss": 1.4504694938659668}, {"step": 381, "epoch": 8, "train_loss": 1.3934030532836914}, {"step": 382, "epoch": 8, "train_loss": 1.3497314453125}, {"step": 383, "epoch": 8, "train_loss": 1.1988223791122437}, {"step": 384, "epoch": 8, "train_loss": 1.1235212087631226}, {"step": 385, "epoch": 8, "train_loss": 1.3399910926818848}, {"step": 386, "epoch": 8, "train_loss": 1.4283431768417358}, {"step": 387, "epoch": 8, "train_loss": 1.311982274055481}, {"step": 388, "epoch": 8, "train_loss": 1.351693868637085}, {"step": 389, "epoch": 8, "train_loss": 1.5409446954727173}, {"step": 390, "epoch": 8, "train_loss": 1.5259792804718018}, {"step": 391, "epoch": 8, "train_loss": 1.601946473121643}, {"step": 392, "epoch": 8, "train_loss": 1.5326645374298096}, {"step": 393, "epoch": 8, "train_loss": 1.5428593158721924}, {"step": 394, "epoch": 8, "train_loss": 1.408697485923767}, {"step": 395, "epoch": 8, "train_loss": 1.241033673286438}, {"step": 396, "epoch": 8, "train_loss": 1.1988921165466309}, {"step": 397, "epoch": 8, "train_loss": 1.0243501663208008}, {"step": 398, "epoch": 8, "train_loss": 1.334486961364746}, {"step": 399, "epoch": 8, "train_loss": 1.205808162689209}, {"step": 400, "epoch": 8, "train_loss": 1.3872802257537842}, {"step": 401, "epoch": 8, "train_loss": 1.2727793455123901}, {"step": 402, "epoch": 8, "train_loss": 1.2286187410354614}, {"step": 403, "epoch": 8, "train_loss": 1.4718501567840576}, {"step": 404, "epoch": 8, "train_loss": 1.3966299295425415}, {"step": 405, "epoch": 8, "train_loss": 1.5416147708892822}, {"step": 406, "epoch": 8, "train_loss": 1.0872350931167603}, {"step": 407, "epoch": 8, "train_loss": 1.3590391874313354}, {"step": 408, "epoch": 8, "train_loss": 0.9587218761444092}, {"step": 409, "epoch": 9, "train_loss": 1.2174500226974487}, {"step": 410, "epoch": 9, "train_loss": 1.2562718391418457}, {"step": 411, "epoch": 9, "train_loss": 1.3811700344085693}, {"step": 412, "epoch": 9, "train_loss": 1.1598758697509766}, {"step": 413, "epoch": 9, "train_loss": 1.1876256465911865}, {"step": 414, "epoch": 9, "train_loss": 1.2681523561477661}, {"step": 415, "epoch": 9, "train_loss": 1.2985705137252808}, {"step": 416, "epoch": 9, "train_loss": 1.058836817741394}, {"step": 417, "epoch": 9, "train_loss": 1.1514856815338135}, {"step": 418, "epoch": 9, "train_loss": 1.3890764713287354}, {"step": 419, "epoch": 9, "train_loss": 1.2957621812820435}, {"step": 420, "epoch": 9, "train_loss": 1.3829787969589233}, {"step": 421, "epoch": 9, "train_loss": 1.2596138715744019}, {"step": 422, "epoch": 9, "train_loss": 1.1819392442703247}, {"step": 423, "epoch": 9, "train_loss": 0.9573414325714111}, {"step": 424, "epoch": 9, "train_loss": 1.1226325035095215}, {"step": 425, "epoch": 9, "train_loss": 1.3706605434417725}, {"step": 426, "epoch": 9, "train_loss": 1.1608312129974365}, {"step": 427, "epoch": 9, "train_loss": 1.8156522512435913}, {"step": 428, "epoch": 9, "train_loss": 1.400689959526062}, {"step": 429, "epoch": 9, "train_loss": 1.0238456726074219}, {"step": 430, "epoch": 9, "train_loss": 1.4542608261108398}, {"step": 431, "epoch": 9, "train_loss": 1.3790463209152222}, {"step": 432, "epoch": 9, "train_loss": 1.2681206464767456}, {"step": 433, "epoch": 9, "train_loss": 1.3565552234649658}, {"step": 434, "epoch": 9, "train_loss": 1.1162850856781006}, {"step": 435, "epoch": 9, "train_loss": 1.2179341316223145}, {"step": 436, "epoch": 9, "train_loss": 1.104910135269165}, {"step": 437, "epoch": 9, "train_loss": 1.4631462097167969}, {"step": 438, "epoch": 9, "train_loss": 1.2417227029800415}, {"step": 439, "epoch": 9, "train_loss": 1.4293361902236938}, {"step": 440, "epoch": 9, "train_loss": 1.3180428743362427}, {"step": 441, "epoch": 9, "train_loss": 1.4423584938049316}, {"step": 442, "epoch": 9, "train_loss": 1.4038020372390747}, {"step": 443, "epoch": 9, "train_loss": 1.0503029823303223}, {"step": 444, "epoch": 9, "train_loss": 1.4817640781402588}, {"step": 445, "epoch": 9, "train_loss": 1.1617703437805176}, {"step": 446, "epoch": 9, "train_loss": 1.3956336975097656}, {"step": 447, "epoch": 9, "train_loss": 1.4830107688903809}, {"step": 448, "epoch": 9, "train_loss": 1.2319025993347168}, {"step": 449, "epoch": 9, "train_loss": 1.3499350547790527}, {"step": 450, "epoch": 9, "train_loss": 1.1488935947418213}, {"step": 451, "epoch": 9, "train_loss": 1.4756360054016113}, {"step": 452, "epoch": 9, "train_loss": 1.1296128034591675}, {"step": 453, "epoch": 9, "train_loss": 1.0527623891830444}, {"step": 454, "epoch": 9, "train_loss": 1.1381479501724243}, {"step": 455, "epoch": 9, "train_loss": 1.1318855285644531}, {"step": 456, "epoch": 9, "train_loss": 1.1347581148147583}, {"step": 457, "epoch": 9, "train_loss": 0.8823924660682678}, {"step": 458, "epoch": 9, "train_loss": 1.3678158521652222}, {"step": 459, "epoch": 9, "train_loss": 1.6148401498794556}, {"step": 460, "epoch": 10, "train_loss": 1.2812113761901855}, {"step": 461, "epoch": 10, "train_loss": 1.5256719589233398}, {"step": 462, "epoch": 10, "train_loss": 1.410045862197876}, {"step": 463, "epoch": 10, "train_loss": 1.0372323989868164}, {"step": 464, "epoch": 10, "train_loss": 1.3488774299621582}, {"step": 465, "epoch": 10, "train_loss": 1.1328401565551758}, {"step": 466, "epoch": 10, "train_loss": 0.990432620048523}, {"step": 467, "epoch": 10, "train_loss": 1.41197669506073}, {"step": 468, "epoch": 10, "train_loss": 1.0146195888519287}, {"step": 469, "epoch": 10, "train_loss": 1.1644279956817627}, {"step": 470, "epoch": 10, "train_loss": 1.4592145681381226}, {"step": 471, "epoch": 10, "train_loss": 1.1420400142669678}, {"step": 472, "epoch": 10, "train_loss": 1.1411364078521729}, {"step": 473, "epoch": 10, "train_loss": 1.2649585008621216}, {"step": 474, "epoch": 10, "train_loss": 1.17787504196167}, {"step": 475, "epoch": 10, "train_loss": 1.1773737668991089}, {"step": 476, "epoch": 10, "train_loss": 1.128482460975647}, {"step": 477, "epoch": 10, "train_loss": 1.3499943017959595}, {"step": 478, "epoch": 10, "train_loss": 1.2105295658111572}, {"step": 479, "epoch": 10, "train_loss": 1.196251392364502}, {"step": 480, "epoch": 10, "train_loss": 1.2971394062042236}, {"step": 481, "epoch": 10, "train_loss": 0.9095219373703003}, {"step": 482, "epoch": 10, "train_loss": 1.2572052478790283}, {"step": 483, "epoch": 10, "train_loss": 1.2027676105499268}, {"step": 484, "epoch": 10, "train_loss": 1.0182859897613525}, {"step": 485, "epoch": 10, "train_loss": 1.3378278017044067}, {"step": 486, "epoch": 10, "train_loss": 1.0341113805770874}, {"step": 487, "epoch": 10, "train_loss": 1.23157799243927}, {"step": 488, "epoch": 10, "train_loss": 1.5509395599365234}, {"step": 489, "epoch": 10, "train_loss": 1.2087721824645996}, {"step": 490, "epoch": 10, "train_loss": 1.151347279548645}, {"step": 491, "epoch": 10, "train_loss": 1.2206653356552124}, {"step": 492, "epoch": 10, "train_loss": 1.2677406072616577}, {"step": 493, "epoch": 10, "train_loss": 1.1502711772918701}, {"step": 494, "epoch": 10, "train_loss": 1.1397286653518677}, {"step": 495, "epoch": 10, "train_loss": 1.2070465087890625}, {"step": 496, "epoch": 10, "train_loss": 1.2128169536590576}, {"step": 497, "epoch": 10, "train_loss": 1.3430463075637817}, {"step": 498, "epoch": 10, "train_loss": 1.2098528146743774}, {"step": 499, "epoch": 10, "train_loss": 1.3239017724990845}, {"step": 500, "epoch": 10, "train_loss": 1.4419666528701782}, {"step": 501, "epoch": 10, "train_loss": 1.2776960134506226}, {"step": 502, "epoch": 10, "train_loss": 1.2757335901260376}, {"step": 503, "epoch": 10, "train_loss": 1.79107666015625}, {"step": 504, "epoch": 10, "train_loss": 1.4824368953704834}, {"step": 505, "epoch": 10, "train_loss": 1.221818208694458}, {"step": 506, "epoch": 10, "train_loss": 0.9130416512489319}, {"step": 507, "epoch": 10, "train_loss": 1.2745238542556763}, {"step": 508, "epoch": 10, "train_loss": 1.1948761940002441}, {"step": 509, "epoch": 10, "train_loss": 1.1906081438064575}, {"step": 510, "epoch": 10, "train_loss": 1.583165168762207}, {"step": 511, "epoch": 11, "train_loss": 1.0223710536956787}, {"step": 512, "epoch": 11, "train_loss": 1.2626668214797974}, {"step": 513, "epoch": 11, "train_loss": 1.0981608629226685}, {"step": 514, "epoch": 11, "train_loss": 1.0888839960098267}, {"step": 515, "epoch": 11, "train_loss": 1.5600638389587402}, {"step": 516, "epoch": 11, "train_loss": 1.0866048336029053}, {"step": 517, "epoch": 11, "train_loss": 1.4517719745635986}, {"step": 518, "epoch": 11, "train_loss": 1.0570123195648193}, {"step": 519, "epoch": 11, "train_loss": 1.1830008029937744}, {"step": 520, "epoch": 11, "train_loss": 1.113091230392456}, {"step": 521, "epoch": 11, "train_loss": 1.47432279586792}, {"step": 522, "epoch": 11, "train_loss": 1.3130338191986084}, {"step": 523, "epoch": 11, "train_loss": 1.3777332305908203}, {"step": 524, "epoch": 11, "train_loss": 1.265718936920166}, {"step": 525, "epoch": 11, "train_loss": 1.4340380430221558}, {"step": 526, "epoch": 11, "train_loss": 1.1051044464111328}, {"step": 527, "epoch": 11, "train_loss": 1.3717384338378906}, {"step": 528, "epoch": 11, "train_loss": 1.130301594734192}, {"step": 529, "epoch": 11, "train_loss": 1.0625033378601074}, {"step": 530, "epoch": 11, "train_loss": 1.1502363681793213}, {"step": 531, "epoch": 11, "train_loss": 1.2527389526367188}, {"step": 532, "epoch": 11, "train_loss": 1.2176074981689453}, {"step": 533, "epoch": 11, "train_loss": 1.1111149787902832}, {"step": 534, "epoch": 11, "train_loss": 1.1352044343948364}, {"step": 535, "epoch": 11, "train_loss": 1.0184664726257324}, {"step": 536, "epoch": 11, "train_loss": 1.1407294273376465}, {"step": 537, "epoch": 11, "train_loss": 1.1605165004730225}, {"step": 538, "epoch": 11, "train_loss": 1.2981008291244507}, {"step": 539, "epoch": 11, "train_loss": 1.2245277166366577}, {"step": 540, "epoch": 11, "train_loss": 1.3414769172668457}, {"step": 541, "epoch": 11, "train_loss": 1.1103709936141968}, {"step": 542, "epoch": 11, "train_loss": 1.4329909086227417}, {"step": 543, "epoch": 11, "train_loss": 1.518951416015625}, {"step": 544, "epoch": 11, "train_loss": 1.272216558456421}, {"step": 545, "epoch": 11, "train_loss": 0.9710613489151001}, {"step": 546, "epoch": 11, "train_loss": 1.036231279373169}, {"step": 547, "epoch": 11, "train_loss": 1.1028896570205688}, {"step": 548, "epoch": 11, "train_loss": 1.2017265558242798}, {"step": 549, "epoch": 11, "train_loss": 1.1989545822143555}, {"step": 550, "epoch": 11, "train_loss": 1.3918986320495605}, {"step": 551, "epoch": 11, "train_loss": 1.2197096347808838}, {"step": 552, "epoch": 11, "train_loss": 1.1201728582382202}, {"step": 553, "epoch": 11, "train_loss": 1.4271286725997925}, {"step": 554, "epoch": 11, "train_loss": 1.2053871154785156}, {"step": 555, "epoch": 11, "train_loss": 1.2526021003723145}, {"step": 556, "epoch": 11, "train_loss": 1.2245168685913086}, {"step": 557, "epoch": 11, "train_loss": 1.125413179397583}, {"step": 558, "epoch": 11, "train_loss": 1.233806848526001}, {"step": 559, "epoch": 11, "train_loss": 1.1987524032592773}, {"step": 560, "epoch": 11, "train_loss": 1.0569860935211182}, {"step": 561, "epoch": 11, "train_loss": 1.4140286445617676}, {"step": 562, "epoch": 12, "train_loss": 1.2618939876556396}, {"step": 563, "epoch": 12, "train_loss": 1.1011890172958374}, {"step": 564, "epoch": 12, "train_loss": 1.1540706157684326}, {"step": 565, "epoch": 12, "train_loss": 1.542980432510376}, {"step": 566, "epoch": 12, "train_loss": 1.160658597946167}, {"step": 567, "epoch": 12, "train_loss": 1.4467244148254395}, {"step": 568, "epoch": 12, "train_loss": 1.0844197273254395}, {"step": 569, "epoch": 12, "train_loss": 1.3116376399993896}, {"step": 570, "epoch": 12, "train_loss": 1.3947917222976685}, {"step": 571, "epoch": 12, "train_loss": 1.0921558141708374}, {"step": 572, "epoch": 12, "train_loss": 1.152783989906311}, {"step": 573, "epoch": 12, "train_loss": 1.224236249923706}, {"step": 574, "epoch": 12, "train_loss": 1.02676522731781}, {"step": 575, "epoch": 12, "train_loss": 1.1200165748596191}, {"step": 576, "epoch": 12, "train_loss": 1.053667426109314}, {"step": 577, "epoch": 12, "train_loss": 1.2897815704345703}, {"step": 578, "epoch": 12, "train_loss": 1.0745551586151123}, {"step": 579, "epoch": 12, "train_loss": 1.2904680967330933}, {"step": 580, "epoch": 12, "train_loss": 1.1033899784088135}, {"step": 581, "epoch": 12, "train_loss": 1.084072232246399}, {"step": 582, "epoch": 12, "train_loss": 1.2435097694396973}, {"step": 583, "epoch": 12, "train_loss": 1.1547833681106567}, {"step": 584, "epoch": 12, "train_loss": 1.201074481010437}, {"step": 585, "epoch": 12, "train_loss": 0.979174017906189}, {"step": 586, "epoch": 12, "train_loss": 1.1728793382644653}, {"step": 587, "epoch": 12, "train_loss": 1.1426942348480225}, {"step": 588, "epoch": 12, "train_loss": 1.356724739074707}, {"step": 589, "epoch": 12, "train_loss": 1.3755505084991455}, {"step": 590, "epoch": 12, "train_loss": 1.0323851108551025}, {"step": 591, "epoch": 12, "train_loss": 1.0591778755187988}, {"step": 592, "epoch": 12, "train_loss": 1.2074569463729858}, {"step": 593, "epoch": 12, "train_loss": 1.122640609741211}, {"step": 594, "epoch": 12, "train_loss": 1.4393471479415894}, {"step": 595, "epoch": 12, "train_loss": 1.4377446174621582}, {"step": 596, "epoch": 12, "train_loss": 1.0403105020523071}, {"step": 597, "epoch": 12, "train_loss": 1.23905348777771}, {"step": 598, "epoch": 12, "train_loss": 1.1247680187225342}, {"step": 599, "epoch": 12, "train_loss": 1.2066489458084106}, {"step": 600, "epoch": 12, "train_loss": 1.3532108068466187}, {"step": 601, "epoch": 12, "train_loss": 1.271504521369934}, {"step": 602, "epoch": 12, "train_loss": 1.154129147529602}, {"step": 603, "epoch": 12, "train_loss": 1.228076696395874}, {"step": 604, "epoch": 12, "train_loss": 1.417525291442871}, {"step": 605, "epoch": 12, "train_loss": 1.2045634984970093}, {"step": 606, "epoch": 12, "train_loss": 1.3050931692123413}, {"step": 607, "epoch": 12, "train_loss": 1.3063127994537354}, {"step": 608, "epoch": 12, "train_loss": 0.9451706409454346}, {"step": 609, "epoch": 12, "train_loss": 1.3147426843643188}, {"step": 610, "epoch": 12, "train_loss": 1.133904218673706}, {"step": 611, "epoch": 12, "train_loss": 1.1189146041870117}, {"step": 612, "epoch": 12, "train_loss": 1.0384067296981812}, {"step": 613, "epoch": 13, "train_loss": 1.1424602270126343}, {"step": 614, "epoch": 13, "train_loss": 1.2676695585250854}, {"step": 615, "epoch": 13, "train_loss": 0.9222124814987183}, {"step": 616, "epoch": 13, "train_loss": 1.1926103830337524}, {"step": 617, "epoch": 13, "train_loss": 1.301558017730713}, {"step": 618, "epoch": 13, "train_loss": 0.9188756346702576}, {"step": 619, "epoch": 13, "train_loss": 1.3109666109085083}, {"step": 620, "epoch": 13, "train_loss": 1.3051906824111938}, {"step": 621, "epoch": 13, "train_loss": 1.0605463981628418}, {"step": 622, "epoch": 13, "train_loss": 1.030292272567749}, {"step": 623, "epoch": 13, "train_loss": 1.3239147663116455}, {"step": 624, "epoch": 13, "train_loss": 1.083138346672058}, {"step": 625, "epoch": 13, "train_loss": 1.195576786994934}, {"step": 626, "epoch": 13, "train_loss": 1.2291224002838135}, {"step": 627, "epoch": 13, "train_loss": 1.1866518259048462}, {"step": 628, "epoch": 13, "train_loss": 1.2649905681610107}, {"step": 629, "epoch": 13, "train_loss": 1.186177372932434}, {"step": 630, "epoch": 13, "train_loss": 0.8691856265068054}, {"step": 631, "epoch": 13, "train_loss": 1.1661838293075562}, {"step": 632, "epoch": 13, "train_loss": 1.0555742979049683}, {"step": 633, "epoch": 13, "train_loss": 1.192194938659668}, {"step": 634, "epoch": 13, "train_loss": 1.1999287605285645}, {"step": 635, "epoch": 13, "train_loss": 1.0971317291259766}, {"step": 636, "epoch": 13, "train_loss": 1.201804280281067}, {"step": 637, "epoch": 13, "train_loss": 1.1084541082382202}, {"step": 638, "epoch": 13, "train_loss": 1.4947885274887085}, {"step": 639, "epoch": 13, "train_loss": 1.2883538007736206}, {"step": 640, "epoch": 13, "train_loss": 1.322272539138794}, {"step": 641, "epoch": 13, "train_loss": 1.362373948097229}, {"step": 642, "epoch": 13, "train_loss": 1.3557943105697632}, {"step": 643, "epoch": 13, "train_loss": 1.1313847303390503}, {"step": 644, "epoch": 13, "train_loss": 0.9035124182701111}, {"step": 645, "epoch": 13, "train_loss": 0.9769655466079712}, {"step": 646, "epoch": 13, "train_loss": 1.0291227102279663}, {"step": 647, "epoch": 13, "train_loss": 1.0732169151306152}, {"step": 648, "epoch": 13, "train_loss": 0.9942082166671753}, {"step": 649, "epoch": 13, "train_loss": 0.993634045124054}, {"step": 650, "epoch": 13, "train_loss": 0.9607744812965393}, {"step": 651, "epoch": 13, "train_loss": 1.0762453079223633}, {"step": 652, "epoch": 13, "train_loss": 1.1538065671920776}, {"step": 653, "epoch": 13, "train_loss": 1.3625807762145996}, {"step": 654, "epoch": 13, "train_loss": 1.158321738243103}, {"step": 655, "epoch": 13, "train_loss": 1.2069098949432373}, {"step": 656, "epoch": 13, "train_loss": 1.3138110637664795}, {"step": 657, "epoch": 13, "train_loss": 1.188449740409851}, {"step": 658, "epoch": 13, "train_loss": 1.1495569944381714}, {"step": 659, "epoch": 13, "train_loss": 1.3703423738479614}, {"step": 660, "epoch": 13, "train_loss": 1.2102758884429932}, {"step": 661, "epoch": 13, "train_loss": 1.7905042171478271}, {"step": 662, "epoch": 13, "train_loss": 1.0246769189834595}, {"step": 663, "epoch": 13, "train_loss": 1.3258789777755737}, {"step": 664, "epoch": 14, "train_loss": 1.127717137336731}, {"step": 665, "epoch": 14, "train_loss": 1.0332465171813965}, {"step": 666, "epoch": 14, "train_loss": 1.0743285417556763}, {"step": 667, "epoch": 14, "train_loss": 1.115857481956482}, {"step": 668, "epoch": 14, "train_loss": 0.7479763031005859}, {"step": 669, "epoch": 14, "train_loss": 0.9732871055603027}, {"step": 670, "epoch": 14, "train_loss": 1.273051142692566}, {"step": 671, "epoch": 14, "train_loss": 1.3143326044082642}, {"step": 672, "epoch": 14, "train_loss": 1.0996477603912354}, {"step": 673, "epoch": 14, "train_loss": 1.171227216720581}, {"step": 674, "epoch": 14, "train_loss": 1.5335702896118164}, {"step": 675, "epoch": 14, "train_loss": 0.9590219259262085}, {"step": 676, "epoch": 14, "train_loss": 1.1858714818954468}, {"step": 677, "epoch": 14, "train_loss": 1.30558443069458}, {"step": 678, "epoch": 14, "train_loss": 0.8679096698760986}, {"step": 679, "epoch": 14, "train_loss": 1.1650898456573486}, {"step": 680, "epoch": 14, "train_loss": 1.2189247608184814}, {"step": 681, "epoch": 14, "train_loss": 1.5579606294631958}, {"step": 682, "epoch": 14, "train_loss": 1.1204758882522583}, {"step": 683, "epoch": 14, "train_loss": 1.1562411785125732}, {"step": 684, "epoch": 14, "train_loss": 1.2250361442565918}, {"step": 685, "epoch": 14, "train_loss": 0.8656103014945984}, {"step": 686, "epoch": 14, "train_loss": 1.4161994457244873}, {"step": 687, "epoch": 14, "train_loss": 1.3917648792266846}, {"step": 688, "epoch": 14, "train_loss": 1.0350838899612427}, {"step": 689, "epoch": 14, "train_loss": 1.3795149326324463}, {"step": 690, "epoch": 14, "train_loss": 0.9199281930923462}, {"step": 691, "epoch": 14, "train_loss": 1.101170539855957}, {"step": 692, "epoch": 14, "train_loss": 1.1951653957366943}, {"step": 693, "epoch": 14, "train_loss": 1.380308747291565}, {"step": 694, "epoch": 14, "train_loss": 1.0918560028076172}, {"step": 695, "epoch": 14, "train_loss": 1.2562446594238281}, {"step": 696, "epoch": 14, "train_loss": 1.457105278968811}, {"step": 697, "epoch": 14, "train_loss": 1.0571340322494507}, {"step": 698, "epoch": 14, "train_loss": 0.9930568337440491}, {"step": 699, "epoch": 14, "train_loss": 1.1450647115707397}, {"step": 700, "epoch": 14, "train_loss": 1.1704386472702026}, {"step": 701, "epoch": 14, "train_loss": 1.122422218322754}, {"step": 702, "epoch": 14, "train_loss": 1.00203275680542}, {"step": 703, "epoch": 14, "train_loss": 0.9392433166503906}, {"step": 704, "epoch": 14, "train_loss": 1.4345793724060059}, {"step": 705, "epoch": 14, "train_loss": 1.2739801406860352}, {"step": 706, "epoch": 14, "train_loss": 1.0870128870010376}, {"step": 707, "epoch": 14, "train_loss": 1.2381892204284668}, {"step": 708, "epoch": 14, "train_loss": 1.2618812322616577}, {"step": 709, "epoch": 14, "train_loss": 1.135027289390564}, {"step": 710, "epoch": 14, "train_loss": 1.012355923652649}, {"step": 711, "epoch": 14, "train_loss": 1.495747447013855}, {"step": 712, "epoch": 14, "train_loss": 0.9332849979400635}, {"step": 713, "epoch": 14, "train_loss": 1.146153211593628}, {"step": 714, "epoch": 14, "train_loss": 1.4105051755905151}, {"step": 715, "epoch": 15, "train_loss": 0.8600872755050659}, {"step": 716, "epoch": 15, "train_loss": 1.1629034280776978}, {"step": 717, "epoch": 15, "train_loss": 1.6580954790115356}, {"step": 718, "epoch": 15, "train_loss": 1.3321526050567627}, {"step": 719, "epoch": 15, "train_loss": 1.281248688697815}, {"step": 720, "epoch": 15, "train_loss": 1.145982027053833}, {"step": 721, "epoch": 15, "train_loss": 1.077536940574646}, {"step": 722, "epoch": 15, "train_loss": 0.997528612613678}, {"step": 723, "epoch": 15, "train_loss": 0.9965357780456543}, {"step": 724, "epoch": 15, "train_loss": 1.0288118124008179}, {"step": 725, "epoch": 15, "train_loss": 1.4017598628997803}, {"step": 726, "epoch": 15, "train_loss": 1.1136929988861084}, {"step": 727, "epoch": 15, "train_loss": 1.0805120468139648}, {"step": 728, "epoch": 15, "train_loss": 0.8740592002868652}, {"step": 729, "epoch": 15, "train_loss": 1.2169098854064941}, {"step": 730, "epoch": 15, "train_loss": 1.0892045497894287}, {"step": 731, "epoch": 15, "train_loss": 1.1649255752563477}, {"step": 732, "epoch": 15, "train_loss": 1.2656769752502441}, {"step": 733, "epoch": 15, "train_loss": 1.2300647497177124}, {"step": 734, "epoch": 15, "train_loss": 1.2404065132141113}, {"step": 735, "epoch": 15, "train_loss": 0.9550978541374207}, {"step": 736, "epoch": 15, "train_loss": 1.289381980895996}, {"step": 737, "epoch": 15, "train_loss": 1.2753733396530151}, {"step": 738, "epoch": 15, "train_loss": 1.4351016283035278}, {"step": 739, "epoch": 15, "train_loss": 0.9066672325134277}, {"step": 740, "epoch": 15, "train_loss": 0.9561187624931335}, {"step": 741, "epoch": 15, "train_loss": 1.2123217582702637}, {"step": 742, "epoch": 15, "train_loss": 1.079109787940979}, {"step": 743, "epoch": 15, "train_loss": 0.9329649806022644}, {"step": 744, "epoch": 15, "train_loss": 0.9299386143684387}, {"step": 745, "epoch": 15, "train_loss": 0.9275221228599548}, {"step": 746, "epoch": 15, "train_loss": 1.1901832818984985}, {"step": 747, "epoch": 15, "train_loss": 0.9131717681884766}, {"step": 748, "epoch": 15, "train_loss": 0.9420313835144043}, {"step": 749, "epoch": 15, "train_loss": 1.337323546409607}, {"step": 750, "epoch": 15, "train_loss": 1.043592095375061}, {"step": 751, "epoch": 15, "train_loss": 1.0939314365386963}, {"step": 752, "epoch": 15, "train_loss": 1.0460176467895508}, {"step": 753, "epoch": 15, "train_loss": 1.190956950187683}, {"step": 754, "epoch": 15, "train_loss": 1.1812450885772705}, {"step": 755, "epoch": 15, "train_loss": 1.4492930173873901}, {"step": 756, "epoch": 15, "train_loss": 1.4190973043441772}, {"step": 757, "epoch": 15, "train_loss": 1.1017550230026245}, {"step": 758, "epoch": 15, "train_loss": 1.2442902326583862}, {"step": 759, "epoch": 15, "train_loss": 1.3269327878952026}, {"step": 760, "epoch": 15, "train_loss": 1.2342264652252197}, {"step": 761, "epoch": 15, "train_loss": 1.0590875148773193}, {"step": 762, "epoch": 15, "train_loss": 1.0748544931411743}, {"step": 763, "epoch": 15, "train_loss": 1.1862491369247437}, {"step": 764, "epoch": 15, "train_loss": 1.1149697303771973}, {"step": 765, "epoch": 15, "train_loss": 1.2927488088607788}, {"step": 766, "epoch": 16, "train_loss": 1.4585139751434326}, {"step": 767, "epoch": 16, "train_loss": 1.1822535991668701}, {"step": 768, "epoch": 16, "train_loss": 0.929792046546936}, {"step": 769, "epoch": 16, "train_loss": 1.163090467453003}, {"step": 770, "epoch": 16, "train_loss": 0.9408921003341675}, {"step": 771, "epoch": 16, "train_loss": 1.2817819118499756}, {"step": 772, "epoch": 16, "train_loss": 1.0822267532348633}, {"step": 773, "epoch": 16, "train_loss": 1.0878089666366577}, {"step": 774, "epoch": 16, "train_loss": 1.1291053295135498}, {"step": 775, "epoch": 16, "train_loss": 1.168617844581604}, {"step": 776, "epoch": 16, "train_loss": 1.2518784999847412}, {"step": 777, "epoch": 16, "train_loss": 1.3473540544509888}, {"step": 778, "epoch": 16, "train_loss": 1.1677069664001465}, {"step": 779, "epoch": 16, "train_loss": 1.1892101764678955}, {"step": 780, "epoch": 16, "train_loss": 0.8986772298812866}, {"step": 781, "epoch": 16, "train_loss": 1.1048023700714111}, {"step": 782, "epoch": 16, "train_loss": 1.1109704971313477}, {"step": 783, "epoch": 16, "train_loss": 1.1190074682235718}, {"step": 784, "epoch": 16, "train_loss": 1.1560620069503784}, {"step": 785, "epoch": 16, "train_loss": 1.1540462970733643}, {"step": 786, "epoch": 16, "train_loss": 1.2789685726165771}, {"step": 787, "epoch": 16, "train_loss": 1.0834696292877197}, {"step": 788, "epoch": 16, "train_loss": 0.9340537786483765}, {"step": 789, "epoch": 16, "train_loss": 0.8502696752548218}, {"step": 790, "epoch": 16, "train_loss": 1.1278109550476074}, {"step": 791, "epoch": 16, "train_loss": 1.0632942914962769}, {"step": 792, "epoch": 16, "train_loss": 1.2890095710754395}, {"step": 793, "epoch": 16, "train_loss": 1.160688877105713}, {"step": 794, "epoch": 16, "train_loss": 1.0562940835952759}, {"step": 795, "epoch": 16, "train_loss": 1.0533303022384644}, {"step": 796, "epoch": 16, "train_loss": 1.0854828357696533}, {"step": 797, "epoch": 16, "train_loss": 1.2762627601623535}, {"step": 798, "epoch": 16, "train_loss": 1.1985281705856323}, {"step": 799, "epoch": 16, "train_loss": 0.8504698276519775}, {"step": 800, "epoch": 16, "train_loss": 1.5696431398391724}, {"step": 801, "epoch": 16, "train_loss": 1.1444288492202759}, {"step": 802, "epoch": 16, "train_loss": 1.2495168447494507}, {"step": 803, "epoch": 16, "train_loss": 1.1438854932785034}, {"step": 804, "epoch": 16, "train_loss": 1.228785514831543}, {"step": 805, "epoch": 16, "train_loss": 1.0300025939941406}, {"step": 806, "epoch": 16, "train_loss": 1.2692124843597412}, {"step": 807, "epoch": 16, "train_loss": 0.9816055297851562}, {"step": 808, "epoch": 16, "train_loss": 0.7954145073890686}, {"step": 809, "epoch": 16, "train_loss": 1.1152992248535156}, {"step": 810, "epoch": 16, "train_loss": 1.062171220779419}, {"step": 811, "epoch": 16, "train_loss": 0.9421099424362183}, {"step": 812, "epoch": 16, "train_loss": 1.0227501392364502}, {"step": 813, "epoch": 16, "train_loss": 1.0391054153442383}, {"step": 814, "epoch": 16, "train_loss": 1.3207759857177734}, {"step": 815, "epoch": 16, "train_loss": 1.1923933029174805}, {"step": 816, "epoch": 16, "train_loss": 1.1414164304733276}, {"step": 817, "epoch": 17, "train_loss": 1.307343602180481}, {"step": 818, "epoch": 17, "train_loss": 1.1310913562774658}, {"step": 819, "epoch": 17, "train_loss": 1.2864490747451782}, {"step": 820, "epoch": 17, "train_loss": 1.144839882850647}, {"step": 821, "epoch": 17, "train_loss": 0.9364833235740662}, {"step": 822, "epoch": 17, "train_loss": 1.0752687454223633}, {"step": 823, "epoch": 17, "train_loss": 1.0831738710403442}, {"step": 824, "epoch": 17, "train_loss": 1.0884263515472412}, {"step": 825, "epoch": 17, "train_loss": 0.8321078419685364}, {"step": 826, "epoch": 17, "train_loss": 1.197810173034668}, {"step": 827, "epoch": 17, "train_loss": 1.3042138814926147}, {"step": 828, "epoch": 17, "train_loss": 1.338880181312561}, {"step": 829, "epoch": 17, "train_loss": 1.0756545066833496}, {"step": 830, "epoch": 17, "train_loss": 1.2141740322113037}, {"step": 831, "epoch": 17, "train_loss": 1.2163535356521606}, {"step": 832, "epoch": 17, "train_loss": 1.2278225421905518}, {"step": 833, "epoch": 17, "train_loss": 1.0004873275756836}, {"step": 834, "epoch": 17, "train_loss": 1.2204008102416992}, {"step": 835, "epoch": 17, "train_loss": 0.9649094343185425}, {"step": 836, "epoch": 17, "train_loss": 1.2003920078277588}, {"step": 837, "epoch": 17, "train_loss": 1.2295509576797485}, {"step": 838, "epoch": 17, "train_loss": 1.1460708379745483}, {"step": 839, "epoch": 17, "train_loss": 1.0850372314453125}, {"step": 840, "epoch": 17, "train_loss": 1.1780887842178345}, {"step": 841, "epoch": 17, "train_loss": 0.8716398477554321}, {"step": 842, "epoch": 17, "train_loss": 1.0735448598861694}, {"step": 843, "epoch": 17, "train_loss": 0.9386370182037354}, {"step": 844, "epoch": 17, "train_loss": 0.9273189902305603}, {"step": 845, "epoch": 17, "train_loss": 1.15708327293396}, {"step": 846, "epoch": 17, "train_loss": 1.044198989868164}, {"step": 847, "epoch": 17, "train_loss": 1.2558059692382812}, {"step": 848, "epoch": 17, "train_loss": 0.8260471820831299}, {"step": 849, "epoch": 17, "train_loss": 1.0681450366973877}, {"step": 850, "epoch": 17, "train_loss": 1.1967579126358032}, {"step": 851, "epoch": 17, "train_loss": 1.1953014135360718}, {"step": 852, "epoch": 17, "train_loss": 1.131203055381775}, {"step": 853, "epoch": 17, "train_loss": 1.3266799449920654}, {"step": 854, "epoch": 17, "train_loss": 1.0375841856002808}, {"step": 855, "epoch": 17, "train_loss": 1.2909798622131348}, {"step": 856, "epoch": 17, "train_loss": 1.1700469255447388}, {"step": 857, "epoch": 17, "train_loss": 1.188722014427185}, {"step": 858, "epoch": 17, "train_loss": 1.130475401878357}, {"step": 859, "epoch": 17, "train_loss": 1.3167859315872192}, {"step": 860, "epoch": 17, "train_loss": 1.0974658727645874}, {"step": 861, "epoch": 17, "train_loss": 1.264149785041809}, {"step": 862, "epoch": 17, "train_loss": 1.0965547561645508}, {"step": 863, "epoch": 17, "train_loss": 1.0546146631240845}, {"step": 864, "epoch": 17, "train_loss": 0.9733807444572449}, {"step": 865, "epoch": 17, "train_loss": 1.0600528717041016}, {"step": 866, "epoch": 17, "train_loss": 0.973453164100647}, {"step": 867, "epoch": 17, "train_loss": 1.4154807329177856}, {"step": 868, "epoch": 18, "train_loss": 1.1851505041122437}, {"step": 869, "epoch": 18, "train_loss": 1.0042784214019775}, {"step": 870, "epoch": 18, "train_loss": 1.409247636795044}, {"step": 871, "epoch": 18, "train_loss": 1.0728408098220825}, {"step": 872, "epoch": 18, "train_loss": 0.9057276248931885}, {"step": 873, "epoch": 18, "train_loss": 1.0602126121520996}, {"step": 874, "epoch": 18, "train_loss": 1.0962231159210205}, {"step": 875, "epoch": 18, "train_loss": 1.2225631475448608}, {"step": 876, "epoch": 18, "train_loss": 1.1261367797851562}, {"step": 877, "epoch": 18, "train_loss": 0.9956508874893188}, {"step": 878, "epoch": 18, "train_loss": 0.9732159376144409}, {"step": 879, "epoch": 18, "train_loss": 1.0199310779571533}, {"step": 880, "epoch": 18, "train_loss": 1.2432905435562134}, {"step": 881, "epoch": 18, "train_loss": 0.862113356590271}, {"step": 882, "epoch": 18, "train_loss": 0.9840026497840881}, {"step": 883, "epoch": 18, "train_loss": 0.9975089430809021}, {"step": 884, "epoch": 18, "train_loss": 1.2734564542770386}, {"step": 885, "epoch": 18, "train_loss": 1.1068544387817383}, {"step": 886, "epoch": 18, "train_loss": 1.0331491231918335}, {"step": 887, "epoch": 18, "train_loss": 1.0798677206039429}, {"step": 888, "epoch": 18, "train_loss": 0.9213893413543701}, {"step": 889, "epoch": 18, "train_loss": 1.2948158979415894}, {"step": 890, "epoch": 18, "train_loss": 1.000345230102539}, {"step": 891, "epoch": 18, "train_loss": 1.0781066417694092}, {"step": 892, "epoch": 18, "train_loss": 1.3087228536605835}, {"step": 893, "epoch": 18, "train_loss": 1.238877534866333}, {"step": 894, "epoch": 18, "train_loss": 1.3213460445404053}, {"step": 895, "epoch": 18, "train_loss": 0.8611259460449219}, {"step": 896, "epoch": 18, "train_loss": 1.1554412841796875}, {"step": 897, "epoch": 18, "train_loss": 1.043033242225647}, {"step": 898, "epoch": 18, "train_loss": 0.9896180033683777}, {"step": 899, "epoch": 18, "train_loss": 1.208359718322754}, {"step": 900, "epoch": 18, "train_loss": 1.0543584823608398}, {"step": 901, "epoch": 18, "train_loss": 1.2514711618423462}, {"step": 902, "epoch": 18, "train_loss": 1.0988695621490479}, {"step": 903, "epoch": 18, "train_loss": 1.1975191831588745}, {"step": 904, "epoch": 18, "train_loss": 1.0480129718780518}, {"step": 905, "epoch": 18, "train_loss": 1.2182565927505493}, {"step": 906, "epoch": 18, "train_loss": 1.0127726793289185}, {"step": 907, "epoch": 18, "train_loss": 1.0868074893951416}, {"step": 908, "epoch": 18, "train_loss": 1.1473602056503296}, {"step": 909, "epoch": 18, "train_loss": 1.1222811937332153}, {"step": 910, "epoch": 18, "train_loss": 1.376484751701355}, {"step": 911, "epoch": 18, "train_loss": 1.0038152933120728}, {"step": 912, "epoch": 18, "train_loss": 0.9139716625213623}, {"step": 913, "epoch": 18, "train_loss": 1.5682963132858276}, {"step": 914, "epoch": 18, "train_loss": 1.438535213470459}, {"step": 915, "epoch": 18, "train_loss": 1.0020380020141602}, {"step": 916, "epoch": 18, "train_loss": 1.0577147006988525}, {"step": 917, "epoch": 18, "train_loss": 1.2646679878234863}, {"step": 918, "epoch": 18, "train_loss": 1.437431812286377}, {"step": 919, "epoch": 19, "train_loss": 1.0507376194000244}, {"step": 920, "epoch": 19, "train_loss": 1.4582921266555786}, {"step": 921, "epoch": 19, "train_loss": 0.9663509726524353}, {"step": 922, "epoch": 19, "train_loss": 1.472078561782837}, {"step": 923, "epoch": 19, "train_loss": 1.309277057647705}, {"step": 924, "epoch": 19, "train_loss": 1.16782808303833}, {"step": 925, "epoch": 19, "train_loss": 1.222192645072937}, {"step": 926, "epoch": 19, "train_loss": 1.0497117042541504}, {"step": 927, "epoch": 19, "train_loss": 0.8588772416114807}, {"step": 928, "epoch": 19, "train_loss": 0.7423093318939209}, {"step": 929, "epoch": 19, "train_loss": 1.1904789209365845}, {"step": 930, "epoch": 19, "train_loss": 1.2763957977294922}, {"step": 931, "epoch": 19, "train_loss": 0.8344598412513733}, {"step": 932, "epoch": 19, "train_loss": 1.3684213161468506}, {"step": 933, "epoch": 19, "train_loss": 1.0348379611968994}, {"step": 934, "epoch": 19, "train_loss": 0.7842417359352112}, {"step": 935, "epoch": 19, "train_loss": 0.896765947341919}, {"step": 936, "epoch": 19, "train_loss": 0.9036149382591248}, {"step": 937, "epoch": 19, "train_loss": 0.894201397895813}, {"step": 938, "epoch": 19, "train_loss": 1.0441579818725586}, {"step": 939, "epoch": 19, "train_loss": 1.1960421800613403}, {"step": 940, "epoch": 19, "train_loss": 0.9830530881881714}, {"step": 941, "epoch": 19, "train_loss": 1.3669698238372803}, {"step": 942, "epoch": 19, "train_loss": 1.3303965330123901}, {"step": 943, "epoch": 19, "train_loss": 1.1292024850845337}, {"step": 944, "epoch": 19, "train_loss": 1.1113711595535278}, {"step": 945, "epoch": 19, "train_loss": 1.1099653244018555}, {"step": 946, "epoch": 19, "train_loss": 1.2828627824783325}, {"step": 947, "epoch": 19, "train_loss": 0.8314163684844971}, {"step": 948, "epoch": 19, "train_loss": 1.2684084177017212}, {"step": 949, "epoch": 19, "train_loss": 0.9580198526382446}, {"step": 950, "epoch": 19, "train_loss": 1.1508148908615112}, {"step": 951, "epoch": 19, "train_loss": 1.2415308952331543}, {"step": 952, "epoch": 19, "train_loss": 0.8342804908752441}, {"step": 953, "epoch": 19, "train_loss": 1.2220675945281982}, {"step": 954, "epoch": 19, "train_loss": 1.0661437511444092}, {"step": 955, "epoch": 19, "train_loss": 1.1298208236694336}, {"step": 956, "epoch": 19, "train_loss": 1.2378430366516113}, {"step": 957, "epoch": 19, "train_loss": 1.1182857751846313}, {"step": 958, "epoch": 19, "train_loss": 0.9400322437286377}, {"step": 959, "epoch": 19, "train_loss": 1.243135929107666}, {"step": 960, "epoch": 19, "train_loss": 0.8006356358528137}, {"step": 961, "epoch": 19, "train_loss": 1.1462773084640503}, {"step": 962, "epoch": 19, "train_loss": 1.059453010559082}, {"step": 963, "epoch": 19, "train_loss": 1.2220613956451416}, {"step": 964, "epoch": 19, "train_loss": 0.9483107328414917}, {"step": 965, "epoch": 19, "train_loss": 1.0538259744644165}, {"step": 966, "epoch": 19, "train_loss": 1.0169215202331543}, {"step": 967, "epoch": 19, "train_loss": 1.3305268287658691}, {"step": 968, "epoch": 19, "train_loss": 1.05015230178833}, {"step": 969, "epoch": 19, "train_loss": 1.087952971458435}, {"step": 970, "epoch": 20, "train_loss": 1.1028454303741455}, {"step": 971, "epoch": 20, "train_loss": 1.1016615629196167}, {"step": 972, "epoch": 20, "train_loss": 1.4812973737716675}, {"step": 973, "epoch": 20, "train_loss": 1.02234947681427}, {"step": 974, "epoch": 20, "train_loss": 0.8780060410499573}, {"step": 975, "epoch": 20, "train_loss": 1.11569082736969}, {"step": 976, "epoch": 20, "train_loss": 1.142223834991455}, {"step": 977, "epoch": 20, "train_loss": 0.9501644372940063}, {"step": 978, "epoch": 20, "train_loss": 1.0919075012207031}, {"step": 979, "epoch": 20, "train_loss": 0.8803622126579285}, {"step": 980, "epoch": 20, "train_loss": 0.9308854341506958}, {"step": 981, "epoch": 20, "train_loss": 1.2071592807769775}, {"step": 982, "epoch": 20, "train_loss": 0.9650047421455383}, {"step": 983, "epoch": 20, "train_loss": 0.8944772481918335}, {"step": 984, "epoch": 20, "train_loss": 1.3592054843902588}, {"step": 985, "epoch": 20, "train_loss": 0.9274566769599915}, {"step": 986, "epoch": 20, "train_loss": 0.925446093082428}, {"step": 987, "epoch": 20, "train_loss": 1.2191630601882935}, {"step": 988, "epoch": 20, "train_loss": 1.1908873319625854}, {"step": 989, "epoch": 20, "train_loss": 1.048712968826294}, {"step": 990, "epoch": 20, "train_loss": 1.4063746929168701}, {"step": 991, "epoch": 20, "train_loss": 1.1085700988769531}, {"step": 992, "epoch": 20, "train_loss": 1.105528712272644}, {"step": 993, "epoch": 20, "train_loss": 1.3974043130874634}, {"step": 994, "epoch": 20, "train_loss": 1.170301914215088}, {"step": 995, "epoch": 20, "train_loss": 1.0901908874511719}, {"step": 996, "epoch": 20, "train_loss": 0.8615811467170715}, {"step": 997, "epoch": 20, "train_loss": 1.215399146080017}, {"step": 998, "epoch": 20, "train_loss": 0.9879870414733887}, {"step": 999, "epoch": 20, "train_loss": 1.2838397026062012}, {"step": 1000, "epoch": 20, "train_loss": 0.918836236000061}, {"step": 1001, "epoch": 20, "train_loss": 0.944426953792572}, {"step": 1002, "epoch": 20, "train_loss": 1.0260082483291626}, {"step": 1003, "epoch": 20, "train_loss": 0.8677604794502258}, {"step": 1004, "epoch": 20, "train_loss": 1.0909004211425781}, {"step": 1005, "epoch": 20, "train_loss": 1.3925472497940063}, {"step": 1006, "epoch": 20, "train_loss": 1.020944595336914}, {"step": 1007, "epoch": 20, "train_loss": 1.0856554508209229}, {"step": 1008, "epoch": 20, "train_loss": 0.9883579015731812}, {"step": 1009, "epoch": 20, "train_loss": 1.1087024211883545}, {"step": 1010, "epoch": 20, "train_loss": 1.0595086812973022}, {"step": 1011, "epoch": 20, "train_loss": 0.9641360640525818}, {"step": 1012, "epoch": 20, "train_loss": 1.1258635520935059}, {"step": 1013, "epoch": 20, "train_loss": 1.2262301445007324}, {"step": 1014, "epoch": 20, "train_loss": 1.160402774810791}, {"step": 1015, "epoch": 20, "train_loss": 0.9079842567443848}, {"step": 1016, "epoch": 20, "train_loss": 1.214936375617981}, {"step": 1017, "epoch": 20, "train_loss": 1.205994725227356}, {"step": 1018, "epoch": 20, "train_loss": 1.03614342212677}, {"step": 1019, "epoch": 20, "train_loss": 1.244645357131958}, {"step": 1020, "epoch": 20, "train_loss": 1.141869306564331}], "epochs": [{"epoch": 0, "train_loss": 1.954948770588842, "train_acc": 0.10344827586206896, "val_loss": 1.9430808410869809, "val_acc": 0.13385826771653542, "test_loss": 1.9374512943567015, "test_acc": 0.13333333333333333, "lr": 7e-06}, {"epoch": 1, "train_loss": 1.7348387129788327, "train_acc": 0.33251231527093594, "val_loss": 1.7122106448871883, "val_acc": 0.39763779527559057, "test_loss": 1.7079217971539964, "test_acc": 0.403921568627451, "lr": 6.65e-06}, {"epoch": 2, "train_loss": 1.5809772478535844, "train_acc": 0.41995073891625617, "val_loss": 1.611414042983468, "val_acc": 0.468503937007874, "test_loss": 1.6057655872083179, "test_acc": 0.45098039215686275, "lr": 6.300000000000001e-06}, {"epoch": 3, "train_loss": 1.5166811514370546, "train_acc": 0.43842364532019706, "val_loss": 1.585391502680741, "val_acc": 0.468503937007874, "test_loss": 1.578597092628479, "test_acc": 0.4627450980392157, "lr": 5.950000000000001e-06}, {"epoch": 4, "train_loss": 1.4604528003138275, "train_acc": 0.45073891625615764, "val_loss": 1.56711937404993, "val_acc": 0.47244094488188976, "test_loss": 1.5647139722225714, "test_acc": 0.4666666666666667, "lr": 5.600000000000001e-06}, {"epoch": 5, "train_loss": 1.413614331207839, "train_acc": 0.46921182266009853, "val_loss": 1.565076650596979, "val_acc": 0.468503937007874, "test_loss": 1.5551477759492163, "test_acc": 0.4784313725490196, "lr": 5.2500000000000006e-06}, {"epoch": 6, "train_loss": 1.3744685767319402, "train_acc": 0.49876847290640397, "val_loss": 1.5549807745640671, "val_acc": 0.4763779527559055, "test_loss": 1.5576150515500238, "test_acc": 0.47058823529411764, "lr": 4.9000000000000005e-06}, {"epoch": 7, "train_loss": 1.3509222327782016, "train_acc": 0.4876847290640394, "val_loss": 1.5520871474048283, "val_acc": 0.4645669291338583, "test_loss": 1.548166831334432, "test_acc": 0.4745098039215686, "lr": 4.5500000000000005e-06}, {"epoch": 8, "train_loss": 1.3135904831252074, "train_acc": 0.5295566502463054, "val_loss": 1.5396026222724615, "val_acc": 0.4921259842519685, "test_loss": 1.5503485338360656, "test_acc": 0.4745098039215686, "lr": 4.2000000000000004e-06}, {"epoch": 9, "train_loss": 1.2682431161110037, "train_acc": 0.5381773399014779, "val_loss": 1.534803250643212, "val_acc": 0.49606299212598426, "test_loss": 1.541202219327291, "test_acc": 0.49019607843137253, "lr": 3.85e-06}, {"epoch": 10, "train_loss": 1.2431706477855813, "train_acc": 0.5554187192118226, "val_loss": 1.5237522425614005, "val_acc": 0.48031496062992124, "test_loss": 1.5430163098316567, "test_acc": 0.4745098039215686, "lr": 3.5000000000000004e-06}, {"epoch": 11, "train_loss": 1.2191355991833315, "train_acc": 0.5578817733990148, "val_loss": 1.5280547207734716, "val_acc": 0.5, "test_loss": 1.5574630246442907, "test_acc": 0.4745098039215686, "lr": 3.1500000000000003e-06}, {"epoch": 12, "train_loss": 1.2027218782255802, "train_acc": 0.562807881773399, "val_loss": 1.5244964173459632, "val_acc": 0.5, "test_loss": 1.5408465820200303, "test_acc": 0.48627450980392156, "lr": 2.8000000000000003e-06}, {"epoch": 13, "train_loss": 1.1763291587970528, "train_acc": 0.5788177339901478, "val_loss": 1.5119325936309935, "val_acc": 0.5, "test_loss": 1.5353725886812397, "test_acc": 0.49019607843137253, "lr": 2.4500000000000003e-06}, {"epoch": 14, "train_loss": 1.1669318905017647, "train_acc": 0.5985221674876847, "val_loss": 1.5111968695648073, "val_acc": 0.5039370078740157, "test_loss": 1.528935289850422, "test_acc": 0.4784313725490196, "lr": 2.1000000000000002e-06}, {"epoch": 15, "train_loss": 1.1475165236759655, "train_acc": 0.603448275862069, "val_loss": 1.5057796859365749, "val_acc": 0.5, "test_loss": 1.53960803677054, "test_acc": 0.4823529411764706, "lr": 1.7500000000000002e-06}, {"epoch": 16, "train_loss": 1.1269929931668812, "train_acc": 0.6169950738916257, "val_loss": 1.5035949551214383, "val_acc": 0.5039370078740157, "test_loss": 1.533010075606552, "test_acc": 0.4784313725490196, "lr": 1.4000000000000001e-06}, {"epoch": 17, "train_loss": 1.1273550840434183, "train_acc": 0.6120689655172414, "val_loss": 1.4980100130471659, "val_acc": 0.5039370078740157, "test_loss": 1.5257888279709162, "test_acc": 0.4784313725490196, "lr": 1.0500000000000001e-06}, {"epoch": 18, "train_loss": 1.1234268143846484, "train_acc": 0.6231527093596059, "val_loss": 1.5026935883394377, "val_acc": 0.5039370078740157, "test_loss": 1.5308551783655204, "test_acc": 0.4823529411764706, "lr": 7.000000000000002e-07}, {"epoch": 19, "train_loss": 1.0979512131272866, "train_acc": 0.6194581280788177, "val_loss": 1.5008211642738403, "val_acc": 0.49606299212598426, "test_loss": 1.532022480871163, "test_acc": 0.4745098039215686, "lr": 3.500000000000001e-07}, {"epoch": 20, "train_loss": 1.0937629943997988, "train_acc": 0.6342364532019704, "val_loss": 1.4961863390104038, "val_acc": 0.5118110236220472, "test_loss": 1.5278072805965648, "test_acc": 0.47058823529411764, "lr": 0.0}]}